joythief/__init__.py
joythief/compound.py
joythief/core.py
joythief/data_structures.py
joythief/numbers.py
joythief/objects.py
joythief/py.typed
joythief/strings.py
joythief-0.8.1.dist-info/METADATA
joythief-0.8.1.dist-info/WHEEL
joythief-0.8.1.dist-info/licenses/LICENSE
joythief-0.8.1.dist-info/RECORD
