Metadata-Version: 2.4
Name: joythief
Version: 0.8.1
Summary: Comparison is the thief of joy
License-Expression: ISC
License-File: LICENSE
Author: Jonathan Sharpe
Author-email: mail@jonrshar.pe
Requires-Python: >=3.9
Classifier: Development Status :: 4 - Beta
Classifier: Environment :: Other Environment
Classifier: Intended Audience :: Developers
Classifier: Natural Language :: English
Classifier: Operating System :: OS Independent
Classifier: Programming Language :: Python :: 3
Classifier: Programming Language :: Python :: 3.9
Classifier: Programming Language :: Python :: 3.10
Classifier: Programming Language :: Python :: 3.11
Classifier: Programming Language :: Python :: 3.12
Classifier: Programming Language :: Python :: 3.13
Classifier: Programming Language :: Python :: 3.14
Classifier: Topic :: Software Development :: Testing
Classifier: Topic :: Utilities
Classifier: Typing :: Typed
Project-URL: Coverage, https://coveralls.io/github/textbook/joythief
Project-URL: Documentation, https://joythief.readthedocs.io/
Project-URL: Issues, https://github.com/textbook/joythief/issues
Project-URL: Repository, https://github.com/textbook/joythief
Project-URL: Sponsor, https://ko-fi.com/textbook
